carconnectivity/__init__.py
carconnectivity/_version.py
carconnectivity/attributes.py
carconnectivity/battery.py
carconnectivity/carconnectivity.py
carconnectivity/carconnectivity_base.py
carconnectivity/charging.py
carconnectivity/charging_connector.py
carconnectivity/charging_station.py
carconnectivity/climatization.py
carconnectivity/command_impl.py
carconnectivity/commands.py
carconnectivity/connectors.py
carconnectivity/doors.py
carconnectivity/drive.py
carconnectivity/enums.py
carconnectivity/errors.py
carconnectivity/fuel_tank.py
carconnectivity/garage.py
carconnectivity/image_util.py
carconnectivity/images.py
carconnectivity/interfaces.py
carconnectivity/json_util.py
carconnectivity/lights.py
carconnectivity/location.py
carconnectivity/maintenance.py
carconnectivity/objects.py
carconnectivity/observable.py
carconnectivity/plugins.py
carconnectivity/position.py
carconnectivity/software.py
carconnectivity/units.py
carconnectivity/util.py
carconnectivity/vehicle.py
carconnectivity/window_heating.py
carconnectivity/windows.py
carconnectivity/utils/__init__.py
carconnectivity/utils/timeout_lock.py
carconnectivity-0.11.8.dist-info/licenses/LICENSE
carconnectivity_connectors/base/__init__.py
carconnectivity_connectors/base/connector.py
carconnectivity_connectors/base/ui/connector_ui.py
carconnectivity_plugins/base/__init__.py
carconnectivity_plugins/base/plugin.py
carconnectivity_plugins/base/ui/plugin_ui.py
carconnectivity_services/__init__.py
carconnectivity_services/base/__init__.py
carconnectivity_services/base/service.py
carconnectivity_services/location/__init__.py
carconnectivity_services/location/geofence_location_service.py
carconnectivity_services/location/location_service.py
carconnectivity_services/location/osm_location_service.py
carconnectivity-0.11.8.dist-info/METADATA
carconnectivity-0.11.8.dist-info/WHEEL
carconnectivity-0.11.8.dist-info/entry_points.txt
carconnectivity-0.11.8.dist-info/top_level.txt
carconnectivity-0.11.8.dist-info/RECORD
