Metadata-Version: 2.4
Name: carconnectivity
Version: 0.11.8
Summary: Library for retrieving information from car connectivity services
Author: Till Steinbach
License-Expression: MIT
Classifier: Development Status :: 3 - Alpha
Classifier: Intended Audience :: Developers
Classifier: Programming Language :: Python :: 3.9
Classifier: Programming Language :: Python :: 3.10
Classifier: Programming Language :: Python :: 3.11
Classifier: Programming Language :: Python :: 3.12
Classifier: Programming Language :: Python :: 3.13
Classifier: Programming Language :: Python :: 3.14
Classifier: Topic :: Software Development :: Libraries
Requires-Python: >=3.9
License-File: LICENSE
Requires-Dist: argparse
Requires-Dist: cryptography
Requires-Dist: JSON_minify~=0.3.0
Requires-Dist: pytimeparse~=1.1.8
Requires-Dist: ntplib~=0.4.0
Requires-Dist: haversine~=2.9.0
Requires-Dist: requests~=2.32.5
Provides-Extra: connectors
Requires-Dist: carconnectivity-connector-volkswagen>=0.10.1; extra == "connectors"
Requires-Dist: carconnectivity-connector-skoda>=0.11.7; extra == "connectors"
Requires-Dist: carconnectivity-connector-seatcupra>=0.5.1; extra == "connectors"
Requires-Dist: carconnectivity-connector-tronity>=0.7.1; extra == "connectors"
Provides-Extra: plugins
Requires-Dist: carconnectivity-plugin-mqtt>=0.9.1; extra == "plugins"
Requires-Dist: carconnectivity-plugin-mqtt_homeassistant>=0.6.1; extra == "plugins"
Requires-Dist: carconnectivity-plugin-abrp>=0.8.1; extra == "plugins"
Requires-Dist: carconnectivity-plugin-homekit>=0.7.4; extra == "plugins"
Requires-Dist: carconnectivity-plugin-webui>=0.7; extra == "plugins"
Requires-Dist: carconnectivity-plugin-database>=0.3; extra == "plugins"
Provides-Extra: images
Requires-Dist: pillow~=12.1.0; extra == "images"
Requires-Dist: ascii_magic~=2.7.2; extra == "images"
Provides-Extra: all
Requires-Dist: carconnectivity[connectors,images,plugins]; extra == "all"
Dynamic: license-file
